pywebdoc/__init__.py
pywebdoc/cli.py
pywebdoc/error.py
pywebdoc/logger.py
pywebdoc/packages.html.jinja
pywebdoc/packages.py
pywebdoc/pip.py
pywebdoc/style.css
pywebdoc/template.py
pywebdoc/url.py
pywebdoc-0.0.1.dist-info/LICENSE
pywebdoc-0.0.1.dist-info/METADATA
pywebdoc-0.0.1.dist-info/WHEEL
pywebdoc-0.0.1.dist-info/entry_points.txt
pywebdoc-0.0.1.dist-info/top_level.txt
pywebdoc-0.0.1.dist-info/zip-safe
pywebdoc-0.0.1.dist-info/RECORD
