Metadata-Version: 2.1
Name: pywebdoc
Version: 0.0.1
Summary: 
Home-page: https://github.com/Quentin18/pywebdoc
Author: Quentin Deschamps
Author-email: quentindeschamps18@gmail.com
License: MIT
Project-URL: Documentation, https://pywebdoc.readthedocs.io/en/latest/
Project-URL: Travis, https://travis-ci.org/github/Quentin18/pywebdoc/
Project-URL: Source Code, https://github.com/Quentin18/pywebdoc/
Keywords: documentation cli click url pypi
Platform: any
Classifier: License :: OSI Approved :: MIT License
Classifier: Natural Language :: English
Classifier: Operating System :: OS Independent
Classifier: Programming Language :: Python :: 3
Classifier: Programming Language :: Python :: 3.6
Classifier: Programming Language :: Python :: 3.7
Classifier: Programming Language :: Python :: 3.8
Classifier: Topic :: Documentation
Requires-Python: >=3
Requires-Dist: click
Requires-Dist: colorlog
Requires-Dist: jinja2
Requires-Dist: requests
Requires-Dist: tqdm
